titus/P.py
titus/__init__.py
titus/datatype.py
titus/errors.py
titus/fcn.py
titus/genpy.py
titus/options.py
titus/pfaast.py
titus/prettypfa.py
titus/reader.py
titus/signature.py
titus/util.py
titus/version.py
titus/inspector/__init__.py
titus/inspector/defs.py
titus/inspector/jsongadget.py
titus/inspector/main.py
titus/inspector/parser.py
titus/inspector/pfagadget.py
titus/lib/__init__.py
titus/lib/array.py
titus/lib/bytes.py
titus/lib/cast.py
titus/lib/core.py
titus/lib/enum.py
titus/lib/fixed.py
titus/lib/impute.py
titus/lib/interp.py
titus/lib/kernel.py
titus/lib/la.py
titus/lib/link.py
titus/lib/map.py
titus/lib/metric.py
titus/lib/parse.py
titus/lib/pfamath.py
titus/lib/pfastring.py
titus/lib/pfatime.py
titus/lib/rand.py
titus/lib/regex.py
titus/lib/spec.py
titus/lib/model/__init__.py
titus/lib/model/cluster.py
titus/lib/model/naive.py
titus/lib/model/neighbor.py
titus/lib/model/neural.py
titus/lib/model/reg.py
titus/lib/model/svm.py
titus/lib/model/tree.py
titus/lib/prob/__init__.py
titus/lib/prob/dist.py
titus/lib/stat/__init__.py
titus/lib/stat/change.py
titus/lib/stat/pfatest.py
titus/lib/stat/sample.py
titus/producer/__init__.py
titus/producer/cart.py
titus/producer/chain.py
titus/producer/expression.py
titus/producer/kmeans.py
titus/producer/tools.py
titus/producer/transformation.py
titus2-1.2.1.data/scripts/pfachain
titus2-1.2.1.data/scripts/pfaexternalize
titus2-1.2.1.data/scripts/pfainspector
titus2-1.2.1.data/scripts/pfarandom
titus2-1.2.1.data/scripts/pfasize
titus2-1.2.1.dist-info/LICENSE
titus2-1.2.1.dist-info/METADATA
titus2-1.2.1.dist-info/WHEEL
titus2-1.2.1.dist-info/top_level.txt
titus2-1.2.1.dist-info/RECORD
