Metadata-Version: 2.1
Name: titus2
Version: 1.2.1
Summary: Python 3 implementation of Portable Format for Analytics (PFA): producer, converter, and consumer.
Home-page: https://realworldpython.guide/titus2/
Author: Ankit Mahato
Author-email: ankit@realworldpython.guide
Project-URL: Source Code, https://github.com/animator/titus2
Project-URL: Bug Tracker, https://github.com/animator/titus2/issues
Project-URL: Documentation, https://realworldpython.guide/titus2/
Keywords: pfa scoring inference pmml titus hadrian machine learning data mining
Classifier: Development Status :: 5 - Production/Stable
Classifier: Intended Audience :: Developers
Classifier: Intended Audience :: Education
Classifier: Intended Audience :: Information Technology
Classifier: Intended Audience :: Science/Research
Classifier: Topic :: Scientific/Engineering
Classifier: Topic :: Scientific/Engineering :: Artificial Intelligence
Classifier: Topic :: Software Development
Classifier: Topic :: Software Development :: Libraries
Classifier: Topic :: Software Development :: Libraries :: Python Modules
Classifier: License :: OSI Approved :: Apache Software License
Classifier: Programming Language :: Python :: 3 :: Only
Classifier: Programming Language :: Python :: 3
Classifier: Programming Language :: Python :: 3.4
Classifier: Programming Language :: Python :: 3.5
Classifier: Programming Language :: Python :: 3.6
Classifier: Programming Language :: Python :: 3.7
Classifier: Programming Language :: Python :: 3.8
Classifier: Programming Language :: Python :: 3.9
Classifier: Natural Language :: English
Requires-Python: >=3.4,<3.10
License-File: LICENSE
Requires-Dist: avro-python3 (>=1.8.2)
Requires-Dist: ply (>=3.11)
Requires-Dist: pyyaml (>=5.1.2)
Requires-Dist: pytz (>=2019.1)
Requires-Dist: numpy (==1.14.0) ; python_version < "3.6"
Requires-Dist: numpy (<1.20,>=1.15.0) ; python_version >= "3.6"
